.coveragerc
.pylintrc
CHANGES.rst
MANIFEST.in
README.rst
setup.cfg
setup.py
tox.ini
sphinxdocs/CHANGES.rst
sphinxdocs/README.rst
sphinxdocs/conf.py
sphinxdocs/index.rst
sphinxdocs/userguide.rst
src/sphinx_invoke.egg-info/PKG-INFO
src/sphinx_invoke.egg-info/SOURCES.txt
src/sphinx_invoke.egg-info/dependency_links.txt
src/sphinx_invoke.egg-info/requires.txt
src/sphinx_invoke.egg-info/top_level.txt
src/sphinxinvoke/__init__.py
src/sphinxinvoke/_version.py
src/sphinxinvoke/exampletasks.py
src/sphinxinvoke/exampletasksnoargs.py
src/sphinxinvoke/ext.py
tests/__init__.py
tests/test_sphinxinvoke.py
tests/expected/cli.xml
tests/expected/cli_noargs.xml
tests/testdocs/cli.rst
tests/testdocs/cli_expected.rst
tests/testdocs/cli_noargs.rst
tests/testdocs/cli_noargs_expected.rst
tests/testdocs/conf.py
tests/testdocs/index.rst