Metadata-Version: 1.1
Name: sphinx-invoke
Version: 0.2
Summary: Sphinx directive for invoke
Home-page: https://github.com/nokia/sphinx-invoke
Author: Petri Huovinen
Author-email: petri.huovinen@nokia.com
License: BSD 3-Clause
Keywords: Sphinx
Platform: UNKNOWN
Classifier: Intended Audience :: Developers
Classifier: License :: OSI Approved :: BSD License
Classifier: Programming Language :: Python :: 2
Classifier: Programming Language :: Python :: 2.7
Classifier: Programming Language :: Python :: 3
Classifier: Programming Language :: Python :: 3.6
Classifier: Topic :: Software Development
